[
{"paiming":"1","mingcheng":"静安","zhanbi":"0.52"},
{"paiming":"2","mingcheng":"嘉定","zhanbi":"0.45"},
{"paiming":"3","mingcheng":"松江","zhanbi":"0.37"},
{"paiming":"4","mingcheng":"徐汇","zhanbi":"0.34"},
{"paiming":"5","mingcheng":"金山","zhanbi":"0.34"},
{"paiming":"6","mingcheng":"虹口","zhanbi":"0.33"},
{"paiming":"7","mingcheng":"闵行","zhanbi":"0.33"},
{"paiming":"8","mingcheng":"奉贤","zhanbi":"0.31"},
{"paiming":"9","mingcheng":"长宁","zhanbi":"0.31"},
{"paiming":"10","mingcheng":"浦东","zhanbi":"0.30"},
{"paiming":"11","mingcheng":"崇明","zhanbi":"0.29"},
{"paiming":"12","mingcheng":"青浦","zhanbi":"0.27"},
{"paiming":"13","mingcheng":"普陀","zhanbi":"0.26"},
{"paiming":"14","mingcheng":"黄浦","zhanbi":"0.23"},
{"paiming":"15","mingcheng":"宝山","zhanbi":"0.22"},
{"paiming":"16","mingcheng":"杨浦","zhanbi":"0.17"}
]